kaspersmicrobit/__init__.py
kaspersmicrobit/bluetoothdevice.py
kaspersmicrobit/errors.py
kaspersmicrobit/kaspersmicrobit.py
kaspersmicrobit/tkinter.py
kaspersmicrobit/bluetoothprofile/__init__.py
kaspersmicrobit/bluetoothprofile/characteristics.py
kaspersmicrobit/bluetoothprofile/services.py
kaspersmicrobit/services/__init__.py
kaspersmicrobit/services/accelerometer.py
kaspersmicrobit/services/buttons.py
kaspersmicrobit/services/device_information.py
kaspersmicrobit/services/event.py
kaspersmicrobit/services/events.py
kaspersmicrobit/services/generic_access.py
kaspersmicrobit/services/io_pin.py
kaspersmicrobit/services/led.py
kaspersmicrobit/services/leddisplay.py
kaspersmicrobit/services/magnetometer.py
kaspersmicrobit/services/temperature.py
kaspersmicrobit/services/uart.py
kaspersmicrobit/services/v1_events.py
kaspersmicrobit/services/v1_legacy_events.py
kaspersmicrobit/services/v2_events.py
kaspersmicrobit-0.7.0.dist-info/licenses/LICENSE.md
kaspersmicrobit-0.7.0.dist-info/METADATA
kaspersmicrobit-0.7.0.dist-info/WHEEL
kaspersmicrobit-0.7.0.dist-info/top_level.txt
kaspersmicrobit-0.7.0.dist-info/RECORD
