Metadata-Version: 2.4
Name: kaspersmicrobit
Version: 0.7.0
Summary: A python package to connect to the Bluetooth LE GATT services of BBC micro:bit devices. Use your micro:bit as a wireless game controller!
Home-page: https://github.com/janickr/kaspersmicrobit
Author: Janick Reynders
License: Mozilla Public License 2.0 (MPL 2.0)
Project-URL: Documentation (en), https://kaspersmicrobit.readthedocs.io/en/stable
Project-URL: Documentation (nl), https://kaspersmicrobit.readthedocs.io/nl/stable
Keywords: microbit,bluetooth,ble,python-for-kids,gatt
Classifier: Programming Language :: Python :: 3
Classifier: Programming Language :: Python :: 3.9
Classifier: Programming Language :: Python :: 3.10
Classifier: Programming Language :: Python :: 3.11
Classifier: Programming Language :: Python :: 3.12
Classifier: Programming Language :: Python :: 3.13
Classifier: Programming Language :: Python :: 3.14
Classifier: License :: OSI Approved :: Mozilla Public License 2.0 (MPL 2.0)
Classifier: Operating System :: OS Independent
Classifier: Topic :: Software Development :: Libraries :: Python Modules
Requires-Python: >=3.9
License-File: LICENSE.md
Requires-Dist: bleak>=1.1.1
Dynamic: license-file
